llmomics/__init__.py
llmomics/cli.py
llmomics/core/__init__.py
llmomics/core/config.py
llmomics/core/llm_provider.py
llmomics/core/query_parser.py
llmomics/data/__init__.py
llmomics/data/fetcher.py
llmomics/data/geo.py
llmomics/data/sra.py
llmomics/pipeline/__init__.py
llmomics/pipeline/generator.py
llmomics/pipeline/templates.py
llmomics-0.1.0.dist-info/entry_points.txt
llmomics-0.1.0.dist-info/LICENSE
llmomics-0.1.0.dist-info/METADATA
llmomics-0.1.0.dist-info/WHEEL
llmomics-0.1.0.dist-info/RECORD
