Metadata-Version: 2.1
Name: llmomics
Version: 0.1.0
Summary: LLM-powered bioinformatics pipeline generation from natural language
Home-page: https://github.com/allanps/llmomics
License: MIT
Keywords: bioinformatics,llm,pipeline,genomics,ai
Author: Allan Paulo
Author-email: allanpaulo2@hotmail.com
Requires-Python: >=3.8
Classifier: Development Status :: 3 - Alpha
Classifier: Intended Audience :: Science/Research
Classifier: License :: OSI Approved :: MIT License
Classifier: Programming Language :: Python :: 3
Classifier: Programming Language :: Python :: 3.8
Classifier: Programming Language :: Python :: 3.9
Classifier: Programming Language :: Python :: 3.10
Classifier: Programming Language :: Python :: 3.11
Classifier: Programming Language :: Python :: 3.12
Classifier: Topic :: Scientific/Engineering :: Bio-Informatics
Requires-Dist: biopython (>=1.80)
Requires-Dist: click (>=8.0)
Requires-Dist: jinja2 (>=3.0)
Requires-Dist: openai (>=1.0)
Requires-Dist: pandas (>=1.5)
Requires-Dist: pydantic (>=2.0)
Requires-Dist: pydantic-settings (>=2.0)
Requires-Dist: python-dotenv (>=1.0)
Requires-Dist: pyyaml (>=6.0)
Requires-Dist: requests (>=2.28)
Requires-Dist: rich (>=13.0)
Project-URL: Documentation, https://github.com/allanps/llmomics
Project-URL: Repository, https://github.com/allanps/llmomics
